{"info": {"language": "Engelsk", "ECTS": 5, "time": "F4A (tirs 13-17)  eller  F5B (ons 13-17)  eller  F1B (tors 13-17)", "level": "Bachelor", "name": "Life science \u00f8velser og dataanalyse I: Biokemi", "course_no": "27024"}, "course_no": "27024", "grade_percentile": 42.77929155313352, "eval_percentiles": {"learning": 31.485355648535563, "worklevel": 28.97489539748954, "good": 35.98326359832636}, "composites": {"beer_points": 5.940383556912981, "quality_points": 5.842856278226586, "beer_percentiles": 63.63636363636363, "quality_percentiles": 46.08585858585859}}