{"info": {"language": "Engelsk", "ECTS": 5, "time": "E5A (ons 8-12)", "level": "Bachelor", "name": "Introduktion til reaktionsteknik", "course_no": "28140"}, "evals": [{"time": "E-18-13", "N_responses": 23, "learning_answers": [17, 5, 1, 0, 0], "participation_answers": [14, 6, 3, 0, 0], "material_answers": [8, 11, 3, 1, 0], "clear_answers": [6, 13, 4, 0, 0], "connection_answers": [16, 5, 2, 0, 0], "worklevel_answers": [0, 0, 15, 7, 1], "prerequisite_answers": [0, 1, 21, 1, 0], "good_answers": [17, 4, 2, 0, 0]}], "eval_points": [{"time": "E-18-13", "learning": 9.23913043478261, "worklevel": 5.978260869565217, "good": 9.130434782608695, "N": 23}], "grades": [{"time": "2021winter", "N_exam": 43, "N_passed": 36, "exam_avg": 5.5, "grade_dist": [9, 5, 6, 7, 9, 4, 3, 2]}, {"time": "2020winter", "N_exam": 33, "N_passed": 24, "exam_avg": 5.8, "grade_dist": [8, 6, 2, 5, 3, 8, 1, 5]}, {"time": "2020summer", "N_exam": 4, "N_passed": 4, "exam_avg": 3.8, "grade_dist": [0, 0, 1, 1, 2, 0, 0, 1]}, {"time": "2019winter", "N_exam": 36, "N_passed": 28, "exam_avg": 5.3, "grade_dist": [10, 2, 3, 6, 7, 5, 3, 4]}, {"time": "2018winter", "N_exam": 32, "N_passed": 24, "exam_avg": 5.4, "grade_dist": [4, 6, 9, 3, 2, 3, 5, 4]}, {"time": "2018summer", "N_exam": 5, "N_passed": 5, "exam_avg": 9.8, "grade_dist": [1, 3, 1, 0, 0, 0, 0, 1]}, {"time": "2017winter", "N_exam": 41, "N_passed": 28, "exam_avg": 4.1, "grade_dist": [5, 5, 4, 2, 12, 13, 0, 3]}, {"time": "2017summer", "N_exam": 8, "N_passed": 5, "exam_avg": 2.4, "grade_dist": [0, 0, 1, 2, 2, 3, 0, 2]}, {"time": "2016winter", "N_exam": 49, "N_passed": 39, "exam_avg": 4.5, "grade_dist": [5, 6, 7, 11, 10, 6, 4, 1]}, {"time": "2015winter", "N_exam": 38, "N_passed": 29, "exam_avg": 5.4, "grade_dist": [4, 8, 7, 5, 5, 8, 1, 1]}, {"time": "2014winter", "N_exam": 40, "N_passed": 27, "exam_avg": 4.2, "grade_dist": [4, 5, 7, 5, 6, 9, 4, 2]}, {"time": "2013winter", "N_exam": 21, "N_passed": 16, "exam_avg": 4.4, "grade_dist": [2, 3, 2, 5, 4, 4, 1, 5]}, {"time": "2012winter", "N_exam": 24, "N_passed": 21, "exam_avg": 6.8, "grade_dist": [4, 5, 8, 2, 2, 2, 1, 2, 6]}, {"time": "2011winter", "N_exam": 29, "N_passed": 20, "exam_avg": 4.8, "grade_dist": [4, 4, 5, 4, 3, 7, 2, 4]}], "course_no": "28140", "grade_percentile": 8.263598326359832, "eval_percentiles": {"learning": 27.732793522267205, "worklevel": 61.13360323886639, "good": 17.27395411605938}, "composites": {"beer_points": 3.411074807373452, "quality_points": 3.5597652081109925, "beer_percentiles": 14.216478190630049, "quality_percentiles": 12.116316639741518}}