{"info": {"language": "Engelsk", "ECTS": 5, "time": "E3A (tirs 8-12)", "level": "Kandidat", "name": "M\u00e5leteknologi inden for rum- og geofysik", "course_no": "30202"}, "grades": [{"time": "2021winter", "N_exam": 40, "N_passed": 40, "exam_avg": 8.2, "grade_dist": [6, 13, 16, 3, 2, 0, 0, 1]}], "course_no": "30202", "grade_percentile": null, "eval_percentiles": {"learning": 79.7843665768194, "worklevel": 15.768194070080861, "good": 97.10242587601077}, "composites": {"beer_points": null, "quality_points": null, "beer_percentiles": null, "quality_percentiles": null}}