{"info": {"language": "Dansk", "ECTS": 5, "time": "F2B (tors 8-12)", "level": "Diplomingeni\u00f8r", "name": "Grundl\u00e6ggende indeklima-, installations- og energidesign 1", "course_no": "41452"}, "course_no": "41452", "grade_percentile": 79.56609485368315, "eval_percentiles": {"learning": 32.74932614555256, "worklevel": 90.56603773584905, "good": 22.035040431266843}, "composites": {"beer_points": 4.770643455590948, "quality_points": 5.212591479802088, "beer_percentiles": 32.79742765273312, "quality_percentiles": 33.440514469453376}}