{"info": {"language": "Engelsk", "ECTS": 5, "time": "Januar", "level": "Kandidat", "name": "Mikro produkt design, udvikling og produktion", "course_no": "41743"}, "grades": [{"time": "2018winter", "N_exam": 14, "N_passed": 14, "exam_avg": 9.7, "grade_dist": [1, 11, 2, 0, 0, 0, 0, 2]}, {"time": "2014winter", "N_exam": 16, "N_passed": 16, "exam_avg": 9.6, "grade_dist": [1, 13, 1, 1, 0, 0, 0, 1]}, {"time": "2012winter", "N_exam": 8, "N_passed": 8, "exam_avg": 10.8, "grade_dist": [3, 5, 0, 0, 0, 0, 0, 3]}, {"time": "2011winter", "N_exam": 12, "N_passed": 12, "exam_avg": 9.8, "grade_dist": [3, 6, 3, 0, 0, 0, 0, 2]}, {"time": "2010winter", "N_exam": 11, "N_passed": 11, "exam_avg": 10.4, "grade_dist": [6, 4, 0, 0, 1, 0, 0, 2]}], "course_no": "41743", "grade_percentile": 12.159434914228052, "eval_percentiles": {"learning": 73.31536388140161, "worklevel": 11.657681940700808, "good": 80.32345013477088}, "composites": {"beer_points": 5.246596654998055, "quality_points": 6.697132546189151, "beer_percentiles": 44.21221864951769, "quality_percentiles": 66.07717041800643}}