{"info": {"language": "Dansk", "ECTS": 10, "time": "Udenfor skema-struktur", "level": "Deltidsdiplom", "name": "Det personlige lederskab og forandring", "course_no": "62L01"}, "course_no": "62L01", "grade_percentile": 62.67029972752044, "eval_percentiles": {"learning": 44.24686192468619, "worklevel": 89.5397489539749, "good": 60.2510460251046}, "composites": {"beer_points": 4.510840824960338, "quality_points": 5.944075695523232, "beer_percentiles": 26.641414141414142, "quality_percentiles": 47.601010101010104}}